py_simple_lorem/__init__.py
py_simple_lorem/py_simple_lorem.py
py_simple_lorem/version.py
py_simple_lorem-0.0.1.dist-info/LICENSE
py_simple_lorem-0.0.1.dist-info/METADATA
py_simple_lorem-0.0.1.dist-info/WHEEL
py_simple_lorem-0.0.1.dist-info/top_level.txt
py_simple_lorem-0.0.1.dist-info/RECORD
